chasha/__init__.py
chasha/core.py
chasha/contrib/__init__.py
chasha/contrib/client_session.py
chasha/contrib/adapters/__init__.py
chasha/contrib/adapters/wsgi.py
chasha/contrib/adapters/yandex.py
chasha-0.0.2.dist-info/LICENSE.txt
chasha-0.0.2.dist-info/METADATA
chasha-0.0.2.dist-info/WHEEL
chasha-0.0.2.dist-info/top_level.txt
chasha-0.0.2.dist-info/RECORD
