Metadata-Version: 2.1
Name: chasha
Version: 0.0.2
Summary: Microframework for serverless functions
Requires-Python: >=3.10
License-File: LICENSE.txt
